 {


  "http" :
  [


    {
      "virtual_host" : {
        "server_name": ["localhost", "www.localhost"],

        "listen" : [
          {"port" : 12343},
          {"port" : 12345},
          {"port" : 12346}
        ],

        "document_root" : "/Users/yiannis/Downloads/wordpress",
        "directory_listing" : true,

        "proxy_pass" : "http://localhost:5000",
        "tcp_nodelay" : true,

        "location" : [
          {"uri" : "*",
          "file_extension" : "php",
          "cgi" : "php-cgi",
          "proxy_pass" : "http://localhost:5000"}
        ]
      }
    },

    {
      "virtual_host" : {
        "server_name": ["*"],

        "listen" : [
          {"port" : 12344,
            "encryption" : true,
            "ssl_certificate" : "/path/to/certificate.crt",
            "ssl_protocols" : ["TLSv1.1","TLSv1.2"]
          }
        ],

        "document_root" : "/Users/yiannis/www/localhost/public_html",
        "directory_listing" : true
      }
    }


  ],

  "server" : {

    "cache" : {
      "total_size" : "102400",
      "maximum_file_size" : "5120",
      "cleanup_percentage" : "15"
    },

    "send_file_chunk_size" : "32768",

    "indexes" : ["index.php", "index.html","index.htm","default.html","default.htm"]
  }



}
